TBdMM/__init__.py
TBdMM/calculations.py
TBdMM/cli.py
TBdMM-0.1.0.dist-info/LICENSE
TBdMM-0.1.0.dist-info/METADATA
TBdMM-0.1.0.dist-info/WHEEL
TBdMM-0.1.0.dist-info/entry_points.txt
TBdMM-0.1.0.dist-info/top_level.txt
TBdMM-0.1.0.dist-info/RECORD
