Metadata-Version: 2.1
Name: TBdMM
Version: 0.1.0
Summary: Compute tight-binding Hamiltonian matrix and d-band moment from a structure
Author-email: Yang Huang <yanghuang91@gmail.com>
License: MIT
Project-URL: Source Code, https://github.com/YangHuang000/TBdMM
Project-URL: Documentation, https://github.com/YangHuang000/TBdMM/wiki
Keywords: d-band,tight-binding,hamiltonian,moment
Classifier: Programming Language :: Python :: 3
Classifier: License :: OSI Approved :: MIT License
Classifier: Operating System :: OS Independent
Requires-Python: >=3.7
License-File: LICENSE
Requires-Dist: numpy>=1.18
Requires-Dist: ase>=3.22.0
Requires-Dist: argparse
